.coveragerc
.mailmap
.stestr.conf
AUTHORS
CONTRIBUTING.rst
ChangeLog
HACKING.rst
LICENSE
README.rst
babel.cfg
requirements.txt
setup.cfg
setup.py
test-requirements.txt
tox.ini
doc/source/conf.py
doc/source/index.rst
doc/source/readme.rst
doc/source/cli/index.rst
doc/source/contributor/contributing.rst
doc/source/contributor/index.rst
doc/source/install/index.rst
doc/source/install/install.rst
doc/source/library/index.rst
pqclient/__init__.py
pqclient/tests/__init__.py
pqclient/tests/base.py
pqclient/tests/test_pqclient.py
python_pqclient.egg-info/PKG-INFO
python_pqclient.egg-info/SOURCES.txt
python_pqclient.egg-info/dependency_links.txt
python_pqclient.egg-info/not-zip-safe
python_pqclient.egg-info/pbr.json
python_pqclient.egg-info/requires.txt
python_pqclient.egg-info/top_level.txt
releasenotes/notes/.placeholder
releasenotes/source/conf.py
releasenotes/source/index.rst
releasenotes/source/unreleased.rst
releasenotes/source/_static/.placeholder
releasenotes/source/_templates/.placeholder